[{"cpu":0,"cpus":2,"disk":4466565120,"diskread":2145169408,"diskwrite":1368125440,"maxdisk":10464022528,"maxmem":1073741824,"maxswap":536870912,"mem":305451008,"name":"n8n","netin":164833659,"netout":27221756,"pid":320540,"pressurecpufull":"0.00","pressurecpusome":"0.36","pressureiofull":"0.00","pressureiosome":"0.00","pressurememoryfull":"0.00","pressurememorysome":"0.00","status":"running","swap":95105024,"tags":"automation;community-script","type":"lxc","uptime":420837,"vmid":103},{"cpu":0,"cpus":1,"disk":939802624,"diskread":2117091328,"diskwrite":1086390272,"maxdisk":8350298112,"maxmem":536870912,"maxswap":536870912,"mem":104816640,"name":"gitea","netin":291950532,"netout":8381572,"pid":1215661,"pressurecpufull":"0.39","pressurecpusome":"2.23","pressureiofull":"0.18","pressureiosome":"0.18","pressurememoryfull":"0.00","pressurememorysome":"0.00","status":"running","swap":47591424,"tags":"backup;git","type":"lxc","uptime":286701,"vmid":113},{"cpu":0,"cpus":2,"disk":7087804416,"diskread":6088896512,"diskwrite":10056478720,"maxdisk":10464022528,"maxmem":3221225472,"maxswap":536870912,"mem":633794560,"name":"mealie","netin":1418334009,"netout":27215183,"pid":3076554,"pressurecpufull":"0.00","pressurecpusome":"0.00","pressureiofull":"0.00","pressureiosome":"0.00","pressurememoryfull":"0.00","pressurememorysome":"0.00","status":"running","swap":3473408,"tags":"community-script;recipes","type":"lxc","uptime":35424,"vmid":114},{"cpu":0,"cpus":2,"disk":1631408128,"diskread":714661888,"diskwrite":180350976,"maxdisk":6249086976,"maxmem":536870912,"maxswap":536870912,"mem":46395392,"name":"tracktor","netin":107719046,"netout":392933,"pid":1269917,"pressurecpufull":"0.00","pressurecpusome":"0.00","pressureiofull":"0.00","pressureiosome":"0.00","pressurememoryfull":"0.00","pressurememorysome":"0.00","status":"running","swap":60702720,"tags":"car;community-script;monitoring","type":"lxc","uptime":280321,"vmid":110},{"cpu":0,"cpus":1,"disk":1541410816,"diskread":3281969152,"diskwrite":1869299712,"maxdisk":2040373248,"maxmem":1073741824,"maxswap":1073741824,"mem":439894016,"name":"adguard","netin":304268517,"netout":22972845,"pid":10852,"pressurecpufull":"0.12","pressurecpusome":"1.33","pressureiofull":"0.12","pressureiosome":"0.12","pressurememoryfull":"0.00","pressurememorysome":"0.00","status":"running","swap":60854272,"tags":"adblock;community-script","type":"lxc","uptime":466811,"vmid":104},{"cpu":0,"cpus":2,"disk":3220656128,"diskread":843464704,"diskwrite":214065152,"maxdisk":4143677440,"maxmem":1073741824,"maxswap":536870912,"mem":89174016,"name":"actualbudget","netin":112552246,"netout":4479633,"pid":1268122,"pressurecpufull":"0.00","pressurecpusome":"0.39","pressureiofull":"0.00","pressureiosome":"0.00","pressurememoryfull":"0.00","pressurememorysome":"0.00","status":"running","swap":54571008,"tags":"community-script;finance;tailscale","type":"lxc","uptime":280491,"vmid":102},{"cpu":0,"cpus":2,"disk":4105175040,"diskread":2018398208,"diskwrite":6043582464,"maxdisk":12573614080,"maxmem":3221225472,"maxswap":536870912,"mem":248221696,"name":"paperless-ngx","netin":195707904,"netout":2115192,"pid":7720,"pressurecpufull":"0.00","pressurecpusome":"0.18","pressureiofull":"0.00","pressureiosome":"0.00","pressurememoryfull":"0.00","pressurememorysome":"0.00","status":"running","swap":456925184,"tags":"community-script;document;management","type":"lxc","uptime":466987,"vmid":111},{"cpu":0,"cpus":1,"disk":1313366016,"diskread":370368512,"diskwrite":91766784,"maxdisk":2040373248,"maxmem":536870912,"maxswap":536870912,"mem":31698944,"name":"glance","netin":108116101,"netout":485500,"pid":1264174,"pressurecpufull":"0.09","pressurecpusome":"0.29","pressureiofull":"0.00","pressureiosome":"0.00","pressurememoryfull":"0.00","pressurememorysome":"0.00","status":"running","swap":1060864,"tags":"community-script;dashboard","type":"lxc","uptime":280927,"vmid":101},{"cpu":0,"cpus":1,"disk":2525462528,"diskread":1682829312,"diskwrite":1020628992,"maxdisk":4143677440,"maxmem":2147483648,"maxswap":1073741824,"mem":362192896,"name":"comics","netin":410051266,"netout":45928292,"pid":8695,"pressurecpufull":"0.00","pressurecpusome":"0.74","pressureiofull":"0.00","pressureiosome":"0.00","pressurememoryfull":"0.00","pressurememorysome":"0.00","status":"running","swap":443281408,"tags":"comic;community-script;ebook;media","type":"lxc","uptime":466976,"vmid":109},{"cpu":0,"cpus":4,"disk":10616041472,"diskread":7204184064,"diskwrite":12300353536,"maxdisk":20957446144,"maxmem":4294967296,"maxswap":536870912,"mem":831979520,"name":"immich","netin":792972933,"netout":3365740,"pid":8282,"pressurecpufull":"0.00","pressurecpusome":"0.00","pressureiofull":"0.00","pressureiosome":"0.00","pressurememoryfull":"0.00","pressurememorysome":"0.00","status":"running","swap":522940416,"tags":"community-script;photos","type":"lxc","uptime":466979,"vmid":108},{"cpu":0,"cpus":2,"disk":2925809664,"diskread":1100627968,"diskwrite":406474752,"maxdisk":4143677440,"maxmem":1073741824,"maxswap":536870912,"mem":125276160,"name":"nginxproxymanager","netin":1695194189,"netout":925619580,"pid":11480,"pressurecpufull":"0.29","pressurecpusome":"0.71","pressureiofull":"0.00","pressureiosome":"0.00","pressurememoryfull":"0.00","pressurememorysome":"0.00","status":"running","swap":22589440,"tags":"community-script;proxy","type":"lxc","uptime":466780,"vmid":106}]
